eheimdigital/__init__.py
eheimdigital/autofeeder.py
eheimdigital/classic_led_ctrl.py
eheimdigital/classic_vario.py
eheimdigital/device.py
eheimdigital/filter.py
eheimdigital/heater.py
eheimdigital/hub.py
eheimdigital/ph_control.py
eheimdigital/py.typed
eheimdigital/reeflex.py
eheimdigital/types.py
eheimdigital-1.6.0.dist-info/METADATA
eheimdigital-1.6.0.dist-info/WHEEL
eheimdigital-1.6.0.dist-info/licenses/LICENSE
eheimdigital-1.6.0.dist-info/RECORD
