Metadata-Version: 2.4
Name: eheimdigital
Version: 1.6.0
Summary: Offers a Python API for the EHEIM Digital smart aquarium devices.
Project-URL: Homepage, https://codeberg.org/autinerd/eheimdigital
License-Expression: MIT
License-File: LICENSE
Classifier: Programming Language :: Python :: 3
Requires-Dist: aiohttp
Requires-Dist: yarl
